PyDeepLib/__init__.py
PyDeepLib/russian_cmd.py
russian_cmd-0.0.2.dist-info/METADATA
russian_cmd-0.0.2.dist-info/WHEEL
russian_cmd-0.0.2.dist-info/top_level.txt
russian_cmd-0.0.2.dist-info/RECORD
