Metadata-Version: 2.1
Name: russian-cmd
Version: 0.0.2
Summary: This is a fun module with some russian commands
Author: nothingdev
Author-email: anisimovd519@gmail.com
Keywords: russian cmd
Classifier: Programming Language :: Python :: 3.11
Classifier: License :: OSI Approved :: MIT License
Classifier: Operating System :: OS Independent
Requires-Python: >=3.6
